[
  {
    "name": "Herb Root",
    "image": "./Icons/Herb_Root.png",
    "category": "Medicine",
    "rarity": "Common",
    "recipe": [ 
      { "name": "Shredded Root", "rarity": "Common", "amount": 10 }, 
      { "name": "Copper Coin", "amount": 50 } 
    ]
  },
  {
    "name": "Reishi",
    "image": "./Icons/Reishi.png",
    "category": "Medicine",
    "rarity": "Common",
    "recipe": [ 
      { "name": "Shredded Mushroom", "rarity": "Common", "amount": 10 }, 
      { "name": "Copper Coin", "amount": 50 } 
    ]
  },
  {
    "name": "Herb Leaf",
    "image": "./Icons/Herb_Leaf.png",
    "category": "Medicine",
    "rarity": "Common",
    "recipe": [ 
      { "name": "Shredded Stem", "rarity": "Common", "amount": 20 }, 
      { "name": "Copper Coin", "amount": 50 } 
    ]
  },













  {
    "name": "[UC] Unihorn Slice",
    "image": "./Icons/Unihorn_Slice.png",
    "category": "Medicine",
    "rarity": "Uncommon",
    "recipe": [ 
      { "name" : "Unihorn Slice", "rarity": "Common", "amount": 20 }, 
      { "name" : "Copper Coin", "amount": 200 }, 
      { "name" : "Energy", "amount": 100 }
    ]
  },
  {
    "name": "[UC] Flower Oil",
    "image": "./Icons/Flower_Oil.png",
    "category": "Medicine",
    "rarity": "Uncommon",
    "recipe": [ 
      { "name" : "Flower Oil", "rarity": "Common", "amount": 20 }, 
      { "name" : "Copper Coin", "amount": 200 }, 
      { "name" : "Energy", "amount": 100 }
    ]
  },
  {
    "name": "[UC] Century Fruit",
    "image": "./Icons/Century_Fruit.png",
    "category": "Medicine",
    "rarity": "Uncommon",
    "recipe": [ 
      { "name" : "Century Fruit", "rarity": "Common", "amount": 20 }, 
      { "name" : "Copper Coin", "amount": 200 }, 
      { "name" : "Energy", "amount": 100 }
    ]
  },
  {
    "name": "[UC] Greater Yang Pill",
    "image": "./Icons/Greater_Yang_Pill.png",
    "category": "Medicine",
    "rarity": "Uncommon",
    "recipe": [ 
      { "name" : "Greater Yang Pill", "rarity": "Common", "amount": 20 }, 
      { "name" : "Copper Coin", "amount": 200 }, 
      { "name" : "Energy", "amount": 100 }
    ]
  },
  {
    "name": "[UC] Greater Yin Pill",
    "image": "./Icons/Greater_Yin_Pill.png",
    "category": "Medicine",
    "rarity": "Uncommon",
    "recipe": [ 
      { "name" : "Greater Yin Pill", "rarity": "Common", "amount": 20 }, 
      { "name" : "Copper Coin", "amount": 200 }, 
      { "name" : "Energy", "amount": 100 }
    ]
  },
  {
    "name": "[UC] Lesser Yang Pill",
    "image": "./Icons/Lesser_Yang_pill.png",
    "category": "Medicine",
    "rarity": "Uncommon",
    "recipe": [ 
      { "name" : "Lesser Yang Pill", "rarity": "Common", "amount": 20 }, 
      { "name" : "Copper Coin", "amount": 200 }, 
      { "name" : "Energy", "amount": 100 }
    ]
  },
  {
    "name": "[UC] Lesser Yin Pill",
    "image": "./Icons/Lesser_Yin_pill.png",
    "category": "Medicine",
    "rarity": "Uncommon",
    "recipe": [ 
      { "name" : "Lesser Yin Pill", "rarity": "Common", "amount": 20 }, 
      { "name" : "Copper Coin", "amount": 200 }, 
      { "name" : "Energy", "amount": 100 }
    ]
  },
  {
    "name": "[UC] Herb Root",
    "image": "./Icons/Herb_Root.png",
    "category": "Medicine",
    "rarity": "Uncommon",
    "recipe": [ 
      { "name" : "Herb Root", "rarity": "Common", "amount": 10 }, 
      { "name" : "Copper Coin", "amount": 200 }, 
      { "name" : "Energy", "amount": 100 }
    ]
  },
  {
    "name": "[UC] Reishi",
    "image": "./Icons/Reishi.png",
    "category": "Medicine",
    "rarity": "Uncommon",
    "recipe": [ 
      { "name" : "Reishi", "rarity": "Common", "amount": 10 }, 
      { "name" : "Copper Coin", "amount": 200 }, 
      { "name" : "Energy", "amount": 100 }
    ]
  },
  {
    "name": "[UC] Herb Leaf",
    "image": "./Icons/Herb_Leaf.png",
    "category": "Medicine",
    "rarity": "Uncommon",
    "recipe": [ 
      { "name" : "Herb Leaf", "rarity": "Common", "amount": 10 }, 
      { "name" : "Copper Coin", "amount": 200 }, 
      { "name" : "Energy", "amount": 100 }
    ]
  },










  {
    "name": "Rare Oil",
    "image": "./Icons/Oil.png",
    "category": "Medicine",
    "rarity": "Rare",
    "recipe": [ 
      { "name" : "Uncommon Oil", "rarity": "Uncommon", "amount": 10 }, 
      { "name" : "Life Elixir", "rarity": "Uncommon", "amount": 12 }, 
      { "name" : "Copper Coin", "amount": 4000 }, 
      { "name" : "Energy", "amount": 2000 }
    ]
  },
  {
    "name": "[R] Unihorn Slice",
    "image": "./Icons/Unihorn_Slice.png",
    "category": "Medicine",
    "rarity": "Rare",
    "recipe": [ 
      { "name" : "[UC] Unihorn Slice", "rarity": "Uncommon", "amount": 20 }, 
      { "name" : "Copper Coin", "amount": 1000 }, 
      { "name" : "Energy", "amount": 500 }
    ]
  },
  {
    "name": "[R] Flower Oil",
    "image": "./Icons/Flower_Oil.png",
    "category": "Medicine",
    "rarity": "Rare",
    "recipe": [ 
      { "name" : "[UC] Flower Oil", "rarity": "Uncommon", "amount": 20 }, 
      { "name" : "Copper Coin", "amount": 1000 }, 
      { "name" : "Energy", "amount": 500 }
    ]
  },
  {
    "name": "[R] Century Fruit",
    "image": "./Icons/Century_Fruit.png",
    "category": "Medicine",
    "rarity": "Rare",
    "recipe": [ 
      { "name" : "[UC] Century Fruit", "rarity": "Uncommon", "amount": 20 }, 
      { "name" : "Copper Coin", "amount": 1000 }, 
      { "name" : "Energy", "amount": 500 }
    ]
  },
  {
    "name": "[R] Snow Panax",
    "image": "./Icons/Snow_Panax.png",
    "category": "Medicine",
    "rarity": "Rare",
    "recipe": [ 
      { "name" : "[UC] Snow Panax", "rarity": "Uncommon", "amount": 10 }, 
      { "name" : "Life Elixir", "rarity": "Uncommon", "amount": 12 }, 
      { "name" : "Copper Coin", "amount": 4000 }, 
      { "name" : "Energy", "amount": 2000 }
    ]
  },
  {
    "name": "[R] Greater Yang Pill",
    "image": "./Icons/Greater_Yang_Pill.png",
    "category": "Medicine",
    "rarity": "Rare",
    "recipe": [ 
      { "name" : "[UC] Greater Yang Pill", "rarity": "Uncommon", "amount": 20 }, 
      { "name" : "Copper Coin", "amount": 1000 }, 
      { "name" : "Energy", "amount": 500 }
    ]
  },
  {
    "name": "[R] Greater Yin Pill",
    "image": "./Icons/Greater_Yin_Pill.png",
    "category": "Medicine",
    "rarity": "Rare",
    "recipe": [ 
      { "name" : "[UC] Greater Yin Pill", "rarity": "Uncommon", "amount": 20 }, 
      { "name" : "Copper Coin", "amount": 1000 }, 
      { "name" : "Energy", "amount": 500 }
    ]
  },
  {
    "name": "[R] Lesser Yang Pill",
    "image": "./Icons/Lesser_Yang_pill.png",
    "category": "Medicine",
    "rarity": "Rare",
    "recipe": [ 
      { "name" : "[UC] Lesser Yang Pill", "rarity": "Uncommon", "amount": 20 }, 
      { "name" : "Copper Coin", "amount": 1000 }, 
      { "name" : "Energy", "amount": 500 }
    ]
  },
  {
    "name": "[R] Lesser Yin Pill",
    "image": "./Icons/Lesser_Yin_pill.png",
    "category": "Medicine",
    "rarity": "Rare",
    "recipe": [ 
      { "name" : "[UC] Lesser Yin Pill", "rarity": "Uncommon", "amount": 20 }, 
      { "name" : "Copper Coin", "amount": 1000 }, 
      { "name" : "Energy", "amount": 500 }
    ]
  },
  {
    "name": "[R] Herb Root",
    "image": "./Icons/Herb_Root.png",
    "category": "Medicine",
    "rarity": "Rare",
    "recipe": [ 
      { "name" : "[UC] Herb Root", "rarity": "Uncommon", "amount": 10 }, 
      { "name" : "Life Elixir", "rarity": "Uncommon", "amount": 2 }, 
      { "name" : "Copper Coin", "amount": 1000 }, 
      { "name" : "Energy", "amount": 500 }
    ]
  },
  {
    "name": "[R] Reishi",
    "image": "./Icons/Reishi.png",
    "category": "Medicine",
    "rarity": "Rare",
    "recipe": [ 
      { "name" : "[UC] Reishi", "rarity": "Uncommon", "amount": 10 }, 
      { "name" : "Life Elixir", "rarity": "Uncommon", "amount":  2 }, 
      { "name" : "Copper Coin", "amount": 1000 }, 
      { "name" : "Energy", "amount": 500 }
    ]
  },
  {
    "name": "[R] Herb Leaf",
    "image": "./Icons/Herb_Leaf.png",
    "category": "Medicine",
    "rarity": "Rare",
    "recipe": [ 
      { "name" : "[UC] Herb Leaf", "rarity": "Uncommon", "amount": 10 }, 
      { "name" : "Life Elixir", "rarity": "Uncommon", "amount": 2 }, 
      { "name" : "Copper Coin", "amount": 1000 }, 
      { "name" : "Energy", "amount": 500 }
    ]
  },















  {
    "name": "Epic Oil",
    "image": "./Icons/Oil.png",
    "category": "Medicine",
    "rarity": "Epic",
    "recipe": [ 
      { "name" : "Uncommon Oil", "rarity": "Uncommon", "amount": 10 }, 
      { "name" : "Life Elixir", "rarity": "Uncommon", "amount": 50 }, 
      { "name" : "Copper Coin", "amount": 20000 }, 
      { "name" : "Energy", "amount": 10000 }
    ]
  },
  {
    "name": "[E] Unihorn Slice",
    "image": "./Icons/Unihorn_Slice.png",
    "category": "Medicine",
    "rarity": "Epic",
    "recipe": [ 
      { "name" : "[R] Unihorn Slice", "rarity": "Rare", "amount": 20 }, 
      { "name" : "Copper Coin", "amount": 10000 }, 
      { "name" : "Energy", "amount": 2500 }
    ]
  },
  {
    "name": "[E] Flower Oil",
    "image": "./Icons/Flower_Oil.png",
    "category": "Medicine",
    "rarity": "Epic",
    "recipe": [ 
      { "name" : "[R] Flower Oil", "rarity": "Rare", "amount": 20 }, 
      { "name" : "Copper Coin", "amount": 10000 }, 
      { "name" : "Energy", "amount": 2500 }
    ]
  },
  {
    "name": "[E] Century Fruit",
    "image": "./Icons/Century_Fruit.png",
    "category": "Medicine",
    "rarity": "Epic",
    "recipe": [ 
      { "name" : "[R] Century Fruit", "rarity": "Rare", "amount": 20 }, 
      { "name" : "Copper Coin", "amount": 10000 }, 
      { "name" : "Energy", "amount": 2500 }
    ]
  },
  {
    "name": "[E] Snow Panax",
    "image": "./Icons/Snow_Panax.png",
    "category": "Medicine",
    "rarity": "Epic",
    "recipe": [ 
      { "name" : "[R] Snow Panax", "rarity": "Rare", "amount": 10 }, 
      { "name" : "Life Elixir", "rarity": "Uncommon", "amount": 50 }, 
      { "name" : "Copper Coin", "amount": 20000 }, 
      { "name" : "Energy", "amount": 10000 }
    ]
  },
  {
    "name": "[E] Greater Yang Pill",
    "image": "./Icons/Greater_Yang_Pill.png",
    "category": "Medicine",
    "rarity": "Epic",
    "recipe": [ 
      { "name" : "[R] Greater Yang Pill", "rarity": "Rare", "amount": 20 }, 
      { "name" : "Copper Coin", "amount": 10000 }, 
      { "name" : "Energy", "amount": 2500 }
    ]
  },
  {
    "name": "[E] Greater Yin Pill",
    "image": "./Icons/Greater_Yin_Pill.png",
    "category": "Medicine",
    "rarity": "Epic",
    "recipe": [ 
      { "name" : "[R] Greater Yin Pill", "rarity": "Rare", "amount": 20 }, 
      { "name" : "Copper Coin", "amount": 10000 }, 
      { "name" : "Energy", "amount": 2500 }
    ]
  },
  {
    "name": "[E] Lesser Yang Pill",
    "image": "./Icons/Lesser_Yang_pill.png",
    "category": "Medicine",
    "rarity": "Epic",
    "recipe": [ 
      { "name" : "[R] Lesser Yang Pill", "rarity": "Rare", "amount": 20 }, 
      { "name" : "Copper Coin", "amount": 10000 }, 
      { "name" : "Energy", "amount": 2500 }
    ]
  },
  {
    "name": "[E] Lesser Yin Pill",
    "image": "./Icons/Lesser_Yin_pill.png",
    "category": "Medicine",
    "rarity": "Epic",
    "recipe": [ 
      { "name" : "[R] Lesser Yin Pill", "rarity": "Rare", "amount": 20 }, 
      { "name" : "Copper Coin", "amount": 10000 }, 
      { "name" : "Energy", "amount": 2500 }
    ]
  },
  {
    "name": "[E] Herb Root",
    "image": "./Icons/Herb_Root.png",
    "category": "Medicine",
    "rarity": "Epic",
    "recipe": [ 
      { "name" : "[R] Herb Root", "rarity": "Rare", "amount": 10 }, 
      { "name" : "Life Elixir", "rarity": "Uncommon", "amount": 10 }, 
      { "name" : "Copper Coin", "amount": 10000 }, 
      { "name" : "Energy", "amount": 2500 }
    ]
  },
  {
    "name": "[E] Reishi",
    "image": "./Icons/Reishi.png",
    "category": "Medicine",
    "rarity": "Epic",
    "recipe": [ 
      { "name" : "[R] Reishi", "rarity": "Rare", "amount": 10 }, 
      { "name" : "Life Elixir", "rarity": "Uncommon", "amount": 10 }, 
      { "name" : "Copper Coin", "amount": 10000 }, 
      { "name" : "Energy", "amount": 2500 }
    ]
  },
  {
    "name": "[E] Herb Leaf",
    "image": "./Icons/Herb_Leaf.png",
    "category": "Medicine",
    "rarity": "Epic",
    "recipe": [ 
      { "name" : "[R] Herb Leaf", "rarity": "Rare", "amount": 10 }, 
      { "name" : "Life Elixir", "rarity": "Uncommon", "amount": 10 }, 
      { "name" : "Copper Coin", "amount": 10000 }, 
      { "name" : "Energy", "amount": 2500 }
    ]
  },















  {
    "name": "[L] Unihorn Slice",
    "image": "./Icons/Unihorn_Slice.png",
    "category": "Medicine",
    "rarity": "Legendary",
    "recipe": [ 
      { "name" : "[E] Unihorn Slice", "rarity": "Epic", "amount": 20 }, 
      { "name" : "Copper Coin", "amount": 50000 }, 
      { "name" : "Energy", "amount": 12500 }
    ]
  },
  {
    "name": "[L] Flower Oil",
    "image": "./Icons/Flower_Oil.png",
    "category": "Medicine",
    "rarity": "Legendary",
    "recipe": [ 
      { "name" : "[E] Flower Oil", "rarity": "Epic", "amount": 20 }, 
      { "name" : "Copper Coin", "amount": 50000 }, 
      { "name" : "Energy", "amount": 12500 }
    ]
  },
  {
    "name": "[L] Century Fruit",
    "image": "./Icons/Century_Fruit.png",
    "category": "Medicine",
    "rarity": "Legendary",
    "recipe": [ 
      { "name" : "[E] Century Fruit", "rarity": "Epic", "amount": 20 }, 
      { "name" : "Copper Coin", "amount": 50000 },
      { "name" : "Energy", "amount": 12500 }
    ]
  },
  {
    "name": "[L] Greater Yang Pill",
    "image": "./Icons/Greater_Yang_Pill.png",
    "category": "Medicine",
    "rarity": "Legendary",
    "recipe": [ 
      { "name" : "[E] Greater Yang Pill", "rarity": "Epic", "amount": 20 }, 
      { "name" : "Copper Coin", "amount": 50000 }, 
      { "name" : "Energy", "amount": 12500 }
    ]
  },
  {
    "name": "[L] Greater Yin Pill",
    "image": "./Icons/Greater_Yin_Pill.png",
    "category": "Medicine",
    "rarity": "Legendary",
    "recipe": [ 
      { "name" : "[E] Greater Yin Pill", "rarity": "Epic", "amount": 20 }, 
      { "name" : "Copper Coin", "amount": 50000 }, 
      { "name" : "Energy", "amount": 12500 }
    ]
  },
  {
    "name": "[L] Lesser Yang Pill",
    "image": "./Icons/Lesser_Yang_pill.png",
    "category": "Medicine",
    "rarity": "Legendary",
    "recipe": [ 
      { "name" : "[E] Lesser Yang Pill", "rarity": "Epic", "amount": 20 }, 
      { "name" : "Copper Coin", "amount": 50000 }, 
      { "name" : "Energy", "amount": 12500 }
    ]
  },
  {
    "name": "[L] Lesser Yin Pill",
    "image": "./Icons/Lesser_Yin_pill.png",
    "category": "Medicine",
    "rarity": "Legendary",
    "recipe": [ 
      { "name" : "[E] Lesser Yin Pill", "rarity": "Epic", "amount": 20 }, 
      { "name" : "Copper Coin", "amount": 50000 }, 
      { "name" : "Energy", "amount": 12500 }
    ]
  },
  {
    "name": "[L] Herb Root",
    "image": "./Icons/Herb_Root.png",
    "category": "Medicine",
    "rarity": "Legendary",
    "recipe": [ 
      { "name" : "[E] Herb Root", "rarity": "Epic", "amount": 10 }, 
      { "name" : "Life Elixir", "rarity": "Uncommon", "amount": 50 }, 
      { "name" : "Copper Coin", "amount": 50000 }, 
      { "name" : "Energy", "amount": 12500 }
    ]
  },
  {
    "name": "[L] Reishi",
    "image": "./Icons/Reishi.png",
    "category": "Medicine",
    "rarity": "Legendary",
    "recipe": [ 
      { "name" : "[E] Reishi", "rarity": "Epic", "amount": 10 }, 
      { "name" : "Life Elixir", "rarity": "Uncommon", "amount": 50 }, 
      { "name" : "Copper Coin", "amount": 50000 }, 
      { "name" : "Energy", "amount": 12500 }
    ]
  },
  {
    "name": "[L] Herb Leaf",
    "image": "./Icons/Herb_Leaf.png",
    "category": "Medicine",
    "rarity": "Legendary",
    "recipe": [ 
      { "name" : "[E] Herb Leaf", "rarity": "Epic", "amount": 10 }, 
      { "name" : "Life Elixir", "rarity": "Uncommon", "amount": 50 }, 
      { "name" : "Copper Coin", "amount": 50000 }, 
      { "name" : "Energy", "amount": 12500 }
    ]
  },



























































  {
    "name": "[UC] Steel",
    "image": "./Icons/Steel.png",
    "category": "Equipaments",
    "rarity": "Uncommon",
    "recipe": [ 
      { "name" : "Broken Ore", "rarity": "Common", "amount": 10 }, 
      { "name" : "Copper Coin", "amount": 400 }, 
      { "name" : "Dark Steel", "amount": 200 }
    ]
  },
  {
    "name": "[UC] Platinum",
    "image": "./Icons/Platinum.png",
    "category": "Equipaments",
    "rarity": "Uncommon",
    "recipe": [ 
      { "name" : "Broken Ore", "rarity": "Common", "amount": 10 }, 
      { "name" : "Copper Coin", "amount": 400 }, 
      { "name" : "Dark Steel", "amount": 200 }
    ]
  },
  {
    "name": "[UC] Evil Minded Orb",
    "image": "./Icons/Evil_Minded_Orb.png",
    "category": "Equipaments",
    "rarity": "Uncommon",
    "recipe": [ 
      { "name" : "Evil Minded Orb", "rarity": "Common", "amount": 10 }, 
      { "name" : "Copper Coin", "amount": 400 }, 
      { "name" : "Dark Steel", "amount": 200 }
    ]
  },
  {
    "name": "[UC] Quintessence",
    "image": "./Icons/Quintessence.png",
    "category": "Equipaments",
    "rarity": "Uncommon",
    "recipe": [ 
      { "name" : "Quintessence", "rarity": "Common", "amount": 10 }, 
      { "name" : "Copper Coin", "amount": 400 }, 
      { "name" : "Dark Steel", "amount": 200 }
    ]
  },
  {
    "name": "[UC] Illuminating Fragment",
    "image": "./Icons/Illuminating_Fragment.png",
    "category": "Equipaments",
    "rarity": "Uncommon",
    "recipe": [ 
      { "name" : "Evil Minded Orb", "rarity": "Common", "amount": 10 }, 
      { "name" : "Copper Coin", "amount": 400 }, 
      { "name" : "Dark Steel", "amount": 200 }
    ]
  },
  {
    "name": "[UC] Moon Shadow Stone",
    "image": "./Icons/Moon_Shadow_Stone.png",
    "category": "Equipaments",
    "rarity": "Uncommon",
    "recipe": [ 
      { "name" : "Moon Shadow Stone", "rarity": "Common", "amount": 10 }, 
      { "name" : "Copper Coin", "amount": 400 }, 
      { "name" : "Dark Steel", "amount": 200 }
    ]
  },
  {
    "name": "[UC] Exorcism Bauble",
    "image": "./Icons/Exorcism_Bauble.png",
    "category": "Equipaments",
    "rarity": "Uncommon",
    "recipe": [ 
      { "name" : "Exorcism Bauble", "rarity": "Common", "amount": 10 }, 
      { "name" : "Copper Coin", "amount": 400 }, 
      { "name" : "Dark Steel", "amount": 200 }
    ]
  },
  {
    "name": "[UC] Anima Stone",
    "image": "./Icons/Anima_Stone.png",
    "category": "Equipaments",
    "rarity": "Uncommon",
    "recipe": [ 
      { "name" : "Anima Stone", "rarity": "Common", "amount": 10 }, 
      { "name" : "Copper Coin", "amount": 400 }, 
      { "name" : "Dark Steel", "amount": 200 }
    ]
  },














  {
    "name": "[R] Steel",
    "image": "./Icons/Steel.png",
    "category": "Equipaments",
    "rarity": "Rare",
    "recipe": [ 
      { "name" : "[UC] Steel", "rarity": "Uncommon", "amount": 10 }, 
      { "name" : "Glittering Powder", "rarity": "Uncommon", "amount": 2 }, 
      { "name" : "Copper Coin", "amount": 2000 }, 
      { "name" : "Dark Steel", "amount": 1000 }
    ]
  },
  {
    "name": "[R] Platinum",
    "image": "./Icons/Platinum.png",
    "category": "Equipaments",
    "rarity": "Rare",
    "recipe": [ 
      { "name" : "[UC] Platinum", "rarity": "Uncommon", "amount": 10 }, 
      { "name" : "Glittering Powder", "rarity": "Uncommon", "amount": 2 }, 
      { "name" : "Copper Coin", "amount": 2000 }, 
      { "name" : "Dark Steel", "amount": 1000 }
    ]
  },
  {
    "name": "[R] Evil Minded Orb",
    "image": "./Icons/Evil_Minded_Orb.png",
    "category": "Equipaments",
    "rarity": "Rare",
    "recipe": [ 
      { "name" : "[UC] Evil Minded Orb", "rarity": "Uncommon", "amount": 10 }, 
      { "name" : "Glittering Powder", "rarity": "Uncommon", "amount": 2 }, 
      { "name" : "Copper Coin", "amount": 2000 }, 
      { "name" : "Dark Steel", "amount": 1000 }
    ]
  },
  {
    "name": "[R] Quintessence",
    "image": "./Icons/Quintessence.png",
    "category": "Equipaments",
    "rarity": "Rare",
    "recipe": [ 
      { "name" : "[UC] Quintessence", "rarity": "Uncommon", "amount": 10 }, 
      { "name" : "Glittering Powder", "rarity": "Uncommon", "amount": 2 }, 
      { "name" : "Copper Coin", "amount": 2000 }, 
      { "name" : "Dark Steel", "amount": 1000 }
    ]
  },
  {
    "name": "[R] Illuminating Fragment",
    "image": "./Icons/Illuminating_Fragment.png",
    "category": "Equipaments",
    "rarity": "Rare",
    "recipe": [ 
      { "name" : "[UC] Illuminating Fragment", "rarity": "Uncommon", "amount": 10 }, 
      { "name" : "Glittering Powder", "rarity": "Uncommon", "amount": 2 }, 
      { "name" : "Copper Coin", "amount": 2000 }, 
      { "name" : "Dark Steel", "amount": 1000 }
    ]
  },
  {
    "name": "[R] Moon Shadow Stone",
    "image": "./Icons/Moon_Shadow_Stone.png",
    "category": "Equipaments",
    "rarity": "Rare",
    "recipe": [ 
      { "name" : "[UC] Moon Shadow Stone", "rarity": "Uncommon", "amount": 10 }, 
      { "name" : "Glittering Powder", "rarity": "Uncommon", "amount": 2 }, 
      { "name" : "Copper Coin", "amount": 2000 }, 
      { "name" : "Dark Steel", "amount": 1000 }
    ]
  },
  {
    "name": "[R] Exorcism Bauble",
    "image": "./Icons/Exorcism_Bauble.png",
    "category": "Equipaments",
    "rarity": "Rare",
    "recipe": [ 
      { "name" : "[UC] Exorcism Bauble", "rarity": "Uncommon", "amount": 10 }, 
      { "name" : "Glittering Powder", "rarity": "Uncommon", "amount": 2 }, 
      { "name" : "Copper Coin", "amount": 2000 }, 
      { "name" : "Dark Steel", "amount": 1000 }
    ]
  },
  {
    "name": "[R] Anima Stone",
    "image": "./Icons/Anima_Stone.png",
    "category": "Equipaments",
    "rarity": "Rare",
    "recipe": [ 
      { "name" : "[UC] Anima Stone", "rarity": "Uncommon", "amount": 10 }, 
      { "name" : "Glittering Powder", "rarity": "Uncommon", "amount": 2 }, 
      { "name" : "Copper Coin", "amount": 2000 }, 
      { "name" : "Dark Steel", "amount": 1000 }
    ]
  },





  {
    "name": "[E] Steel",
    "image": "./Icons/Steel.png",
    "category": "Equipaments",
    "rarity": "Epic",
    "recipe": [ 
      { "name" : "[R] Steel", "rarity": "Rare", "amount": 10 }, 
      { "name" : "Glittering Powder", "rarity": "Uncommon", "amount": 25 }, 
      { "name" : "Copper Coin", "amount": 20000 }, 
      { "name" : "Dark Steel", "amount": 5000 }
    ]
  },
  {
    "name": "[E] Platinum",
    "image": "./Icons/Platinum.png",
    "category": "Equipaments",
    "rarity": "Epic",
    "recipe": [ 
      { "name" : "[R] Platinum", "rarity": "Rare", "amount": 10 }, 
      { "name" : "Glittering Powder", "rarity": "Uncommon", "amount": 25 }, 
      { "name" : "Copper Coin", "amount": 20000 }, 
      { "name" : "Dark Steel", "amount": 5000 }
    ]
  },
  {
    "name": "[E] Evil Minded Orb",
    "image": "./Icons/Evil_Minded_Orb.png",
    "category": "Equipaments",
    "rarity": "Epic",
    "recipe": [ 
      { "name" : "[R] Evil Minded Orb", "rarity": "Rare", "amount": 10 }, 
      { "name" : "Glittering Powder", "rarity": "Uncommon", "amount": 25 }, 
      { "name" : "Copper Coin", "amount": 20000 }, 
      { "name" : "Dark Steel", "amount": 5000 }
    ]
  },
  {
    "name": "[E] Quintessence",
    "image": "./Icons/Quintessence.png",
    "category": "Equipaments",
    "rarity": "Epic",
    "recipe": [ 
      { "name" : "[R] Quintessence", "rarity": "Rare", "amount": 10 }, 
      { "name" : "Glittering Powder", "rarity": "Uncommon", "amount": 25 }, 
      { "name" : "Copper Coin", "amount": 20000 }, 
      { "name" : "Dark Steel", "amount": 5000 }
    ]
  },
  {
    "name": "[E] Illuminating Fragment",
    "image": "./Icons/Illuminating_Fragment.png",
    "category": "Equipaments",
    "rarity": "Epic",
    "recipe": [ 
      { "name" : "[R] Illuminating Fragment", "rarity": "Rare", "amount": 10 }, 
      { "name" : "Glittering Powder", "rarity": "Uncommon", "amount": 25 }, 
      { "name" : "Copper Coin", "amount": 20000 }, 
      { "name" : "Dark Steel", "amount": 5000 }
    ]
  },
  {
    "name": "[E] Moon Shadow Stone",
    "image": "./Icons/Moon_Shadow_Stone.png",
    "category": "Equipaments",
    "rarity": "Epic",
    "recipe": [ 
      { "name" : "[R] Moon Shadow Stone", "rarity": "Rare", "amount": 10 }, 
      { "name" : "Glittering Powder", "rarity": "Uncommon", "amount": 25 }, 
      { "name" : "Copper Coin", "amount": 20000 }, 
      { "name" : "Dark Steel", "amount": 5000 }
    ]
  },
  {
    "name": "[E] Exorcism Bauble",
    "image": "./Icons/Exorcism_Bauble.png",
    "category": "Equipaments",
    "rarity": "Epic",
    "recipe": [ 
      { "name" : "[R] Exorcism Bauble", "rarity": "Rare", "amount": 10 }, 
      { "name" : "Glittering Powder", "rarity": "Uncommon", "amount": 25 }, 
      { "name" : "Copper Coin", "amount": 20000 }, 
      { "name" : "Dark Steel", "amount": 5000 }
    ]
  },
  {
    "name": "[E] Anima Stone",
    "image": "./Icons/Anima_Stone.png",
    "category": "Equipaments",
    "rarity": "Epic",
    "recipe": [ 
      { "name" : "[R] Anima Stone", "rarity": "Rare", "amount": 10 }, 
      { "name" : "Glittering Powder", "rarity": "Uncommon", "amount": 25 }, 
      { "name" : "Copper Coin", "amount": 20000 }, 
      { "name" : "Dark Steel", "amount": 5000 }
    ]
  },







  {
    "name": "[L] Steel",
    "image": "./Icons/Steel.png",
    "category": "Equipaments",
    "rarity": "Legendary",
    "recipe": [ 
      { "name" : "[E] Steel", "rarity": "Epic", "amount": 10 }, 
      { "name" : "Glittering Powder", "rarity": "Uncommon", "amount": 125 }, 
      { "name" : "Copper Coin", "amount": 100000 }, 
      { "name" : "Dark Steel", "amount": 25000 }
    ]
  },
  {
    "name": "[L] Platinum",
    "image": "./Icons/Platinum.png",
    "category": "Equipaments",
    "rarity": "Legendary",
    "recipe": [ 
      { "name" : "[E] Platinum", "rarity": "Epic", "amount": 10 }, 
      { "name" : "Glittering Powder", "rarity": "Uncommon", "amount": 125 }, 
      { "name" : "Copper Coin", "amount": 100000 }, 
      { "name" : "Dark Steel", "amount": 25000 }
    ]
  },
  {
    "name": "[L] Evil Minded Orb",
    "image": "./Icons/Evil_Minded_Orb.png",
    "category": "Equipaments",
    "rarity": "Legendary",
    "recipe": [ 
      { "name" : "[E] Evil Minded Orb", "rarity": "Epic", "amount": 10 }, 
      { "name" : "Glittering Powder", "rarity": "Uncommon", "amount": 125 }, 
      { "name" : "Copper Coin", "amount": 100000 }, 
      { "name" : "Dark Steel", "amount": 25000 }
    ]
  },
  {
    "name": "[L] Quintessence",
    "image": "./Icons/Quintessence.png",
    "category": "Equipaments",
    "rarity": "Legendary",
    "recipe": [ 
      { "name" : "[E] Quintessence", "rarity": "Epic", "amount": 10 }, 
      { "name" : "Glittering Powder", "rarity": "Uncommon", "amount": 125 }, 
      { "name" : "Copper Coin", "amount": 100000 }, 
      { "name" : "Dark Steel", "amount": 25000 }
    ]
  },
  {
    "name": "[L] Illuminating Fragment",
    "image": "./Icons/Illuminating_Fragment.png",
    "category": "Equipaments",
    "rarity": "Legendary",
    "recipe": [ 
      { "name" : "[E] Illuminating Fragment", "rarity": "Epic", "amount": 10 }, 
      { "name" : "Glittering Powder", "rarity": "Uncommon", "amount": 125 }, 
      { "name" : "Copper Coin", "amount": 100000 }, 
      { "name" : "Dark Steel", "amount": 25000 }
    ]
  },
  {
    "name": "[L] Moon Shadow Stone",
    "image": "./Icons/Moon_Shadow_Stone.png",
    "category": "Equipaments",
    "rarity": "Legendary",
    "recipe": [ 
      { "name" : "[E] Moon Shadow Stone", "rarity": "Epic", "amount": 10 }, 
      { "name" : "Glittering Powder", "rarity": "Uncommon", "amount": 125 }, 
      { "name" : "Copper Coin", "amount": 100000 }, 
      { "name" : "Dark Steel", "amount": 25000 }
    ]
  },
  {
    "name": "[L] Exorcism Bauble",
    "image": "./Icons/Exorcism_Bauble.png",
    "category": "Equipaments",
    "rarity": "Legendary",
    "recipe": [ 
      { "name" : "[E] Exorcism Bauble", "rarity": "Epic", "amount": 10 }, 
      { "name" : "Glittering Powder", "rarity": "Uncommon", "amount": 125 }, 
      { "name" : "Copper Coin", "amount": 100000 }, 
      { "name" : "Dark Steel", "amount": 25000 }
    ]
  },
  {
    "name": "[L] Anima Stone",
    "image": "./Icons/Anima_Stone.png",
    "category": "Equipaments",
    "rarity": "Legendary",
    "recipe": [ 
      { "name" : "[E] Anima Stone", "rarity": "Epic", "amount": 10 }, 
      { "name" : "Glittering Powder", "rarity": "Uncommon", "amount": 25 }, 
      { "name" : "Copper Coin", "amount": 100000 }, 
      { "name" : "Dark Steel", "amount": 25000 }
    ]
  },














































  {
    "name": "[UC] Moonlight Magic Stone",
    "image": "./Icons/Moonlight_Magic_Stone.png",
    "category": "Promotions",
    "rarity": "Uncommon",
    "recipe": [ 
      { "name" : "Moonlight Magic Stone", "rarity": "Common", "amount": 10 }, 
      { "name" : "Copper Coin", "amount": 400 }, 
      { "name" : "Dark Steel", "amount": 200 }
    ]
  },
  {
    "name": "[UC] Blue Devil Stone",
    "image": "./Icons/Blue_Devil_Stone.png",
    "category": "Promotions",
    "rarity": "Uncommon",
    "recipe": [ 
      { "name" : "Blue Devil Stone", "rarity": "Common", "amount": 10 }, 
      { "name" : "Copper Coin", "amount": 400 }, 
      { "name" : "Dark Steel", "amount": 200 }
    ]
  },
  {
    "name": "[UC] Purified Water",
    "image": "./Icons/Purified_Water.png",
    "category": "Promotions",
    "rarity": "Uncommon",
    "recipe": [ 
      { "name" : "Purified Water", "rarity": "Common", "amount": 10 }, 
      { "name" : "Copper Coin", "amount": 400 }, 
      { "name" : "Energy", "amount": 200 }
    ]
  },
  {
    "name": "[UC] Virtue Pill",
    "image": "./Icons/Virtue_Pill.png",
    "category": "Promotions",
    "rarity": "Uncommon",
    "recipe": [ 
      { "name" : "Virtue Pill", "rarity": "Common", "amount": 10 }, 
      { "name" : "Copper Coin", "amount": 400 }, 
      { "name" : "Energy", "amount": 200 }
    ]
  },







  {
    "name": "[R] Moonlight Magic Stone",
    "image": "./Icons/Moonlight_Magic_Stone.png",
    "category": "Promotions",
    "rarity": "Rare",
    "recipe": [ 
      { "name" : "[UC] Moonlight Magic Stone", "rarity": "Uncommon", "amount": 10 }, 
      { "name" : "Glittering Powder", "rarity": "Uncommon", "amount": 5 }, 
      { "name" : "Copper Coin", "amount": 2000 }, 
      { "name" : "Dark Steel", "amount": 1000 }
    ]
  },
  {
    "name": "[R] Blue Devil Stone",
    "image": "./Icons/Blue_Devil_Stone.png",
    "category": "Promotions",
    "rarity": "Rare",
    "recipe": [ 
      { "name" : "[UC] Blue Devil Stone", "rarity": "Uncommon", "amount": 10 }, 
      { "name" : "Glittering Powder", "rarity": "Uncommon", "amount": 5 }, 
      { "name" : "Copper Coin", "amount": 2000 }, 
      { "name" : "Dark Steel", "amount": 1000 }
    ]
  },
  {
    "name": "[R] Purified Water",
    "image": "./Icons/Purified_Water.png",
    "category": "Promotions",
    "rarity": "Rare",
    "recipe": [ 
      { "name" : "[UC] Purified Water", "rarity": "Uncommon", "amount": 10 }, 
      { "name" : "Life Elixir", "rarity": "Uncommon", "amount": 10 }, 
      { "name" : "Copper Coin", "amount": 2000 }, 
      { "name" : "Energy", "amount": 1000 }
    ]
  },
  {
    "name": "Rare Virtue Pill",
    "image": "./Icons/Virtue_Pill.png",
    "category": "Promotions",
    "rarity": "Rare",
    "recipe": [ 
      { "name" : "[UC] Virtue Pill", "rarity": "Uncommon", "amount": 10 }, 
      { "name" : "Life Elixir", "rarity": "Uncommon", "amount": 10 }, 
      { "name" : "Copper Coin", "amount": 2000 }, 
      { "name" : "Energy", "amount": 1000 }
    ]
  },






  {
    "name": "[E] Moonlight Magic Stone",
    "image": "./Icons/Moonlight_Magic_Stone.png",
    "category": "Promotions",
    "rarity": "Epic",
    "recipe": [ 
      { "name" : "[R] Moonlight Magic Stone", "rarity": "Rare", "amount": 10 }, 
      { "name" : "Glittering Powder", "rarity": "Uncommon", "amount": 20 }, 
      { "name" : "Copper Coin", "amount": 20000 }, 
      { "name" : "Dark Steel", "amount": 5000 }
    ]
  },
  {
    "name": "[E] Blue Devil Stone",
    "image": "./Icons/Blue_Devil_Stone.png",
    "category": "Promotions",
    "rarity": "Epic",
    "recipe": [ 
      { "name" : "[R] Blue Devil Stone", "rarity": "Rare", "amount": 10 }, 
      { "name" : "Glittering Powder", "rarity": "Uncommon", "amount": 20 }, 
      { "name" : "Copper Coin", "amount": 20000 }, 
      { "name" : "Dark Steel", "amount": 5000 }
    ]
  },
  {
    "name": "[E] Purified Water",
    "image": "./Icons/Purified_Water.png",
    "category": "Promotions",
    "rarity": "Epic",
    "recipe": [ 
      { "name" : "[R] Purified Water", "rarity": "Rare", "amount": 10 }, 
      { "name" : "Life Elixir", "rarity": "Uncommon", "amount": 40 }, 
      { "name" : "Copper Coin", "amount": 20000 }, 
      { "name" : "Energy", "amount": 5000 }
    ]
  },
  {
    "name": "Epic Virtue Pill",
    "image": "./Icons/Virtue_Pill.png",
    "category": "Promotions",
    "rarity": "Epic",
    "recipe": [ 
      { "name" : "Rare Virtue Pill", "rarity": "Rare", "amount": 10 }, 
      { "name" : "Life Elixir", "rarity": "Uncommon", "amount": 40 }, 
      { "name" : "Copper Coin", "amount": 20000 }, 
      { "name" : "Energy", "amount": 5000 }
    ]
  },





  {
    "name": "[L] Moonlight Magic Stone",
    "image": "./Icons/Moonlight_Magic_Stone.png",
    "category": "Promotions",
    "rarity": "Legendary",
    "recipe": [ 
      { "name" : "[E] Moonlight Magic Stone", "rarity": "Epic", "amount": 10 }, 
      { "name" : "Glittering Powder", "rarity": "Uncommon", "amount": 60 }, 
      { "name" : "Copper Coin", "amount": 100000 }, 
      { "name" : "Dark Steel", "amount": 25000 }
    ]
  },
  {
    "name": "[L] Blue Devil Stone",
    "image": "./Icons/Blue_Devil_Stone.png",
    "category": "Promotions",
    "rarity": "Legendary",
    "recipe": [ 
      { "name" : "[E] Blue Devil Stone", "rarity": "Epic", "amount": 10 }, 
      { "name" : "Glittering Powder", "rarity": "Uncommon", "amount": 60 }, 
      { "name" : "Copper Coin", "amount": 100000 }, 
      { "name" : "Dark Steel", "amount": 25000 }
    ]
  },
  {
    "name": "[L] Purified Water",
    "image": "./Icons/Purified_Water.png",
    "category": "Promotions",
    "rarity": "Legendary",
    "recipe": [ 
      { "name" : "[E] Purified Water", "rarity": "Epic", "amount": 10 }, 
      { "name" : "Life Elixir", "rarity": "Uncommon", "amount": 120 }, 
      { "name" : "Copper Coin", "amount": 100000 }, 
      { "name" : "Energy", "amount": 25000 }
    ]
  },
  {
    "name": "Legendary Virtue Pill",
    "image": "./Icons/Virtue_Pill.png",
    "category": "Promotions",
    "rarity": "Legendary",
    "recipe": [ 
      { "name" : "Epic Virtue Pill", "rarity": "Epic", "amount": 10 }, 
      { "name" : "Life Elixir", "rarity": "Uncommon", "amount": 120 }, 
      { "name" : "Copper Coin", "amount": 100000 }, 
      { "name" : "Energy", "amount": 25000 }
    ]
  }
]